{
	"a": {
		"https://usf-cs272-spring2022.github.io/project-web/input/rfcs/index.html": [
			3,
			32
		]
	},
	"and": {
		"https://usf-cs272-spring2022.github.io/project-web/input/rfcs/index.html": [
			10,
			38,
			44,
			53
		]
	},
	"applic": {
		"https://usf-cs272-spring2022.github.io/project-web/input/rfcs/index.html": [
			21
		]
	},
	"architectur": {
		"https://usf-cs272-spring2022.github.io/project-web/input/rfcs/index.html": [
			27
		]
	},
	"comput": {
		"https://usf-cs272-spring2022.github.io/project-web/input/rfcs/index.html": [
			25
		]
	},
	"content": {
		"https://usf-cs272-spring2022.github.io/project-web/input/rfcs/index.html": [
			54
		]
	},
	"determin": {
		"https://usf-cs272-spring2022.github.io/project-web/input/rfcs/index.html": [
			30
		]
	},
	"domain": {
		"https://usf-cs272-spring2022.github.io/project-web/input/rfcs/index.html": [
			35
		]
	},
	"element": {
		"https://usf-cs272-spring2022.github.io/project-web/input/rfcs/index.html": [
			26
		]
	},
	"for": {
		"https://usf-cs272-spring2022.github.io/project-web/input/rfcs/index.html": [
			16
		]
	},
	"format": {
		"https://usf-cs272-spring2022.github.io/project-web/input/rfcs/index.html": [
			5
		]
	},
	"ftp": {
		"https://usf-cs272-spring2022.github.io/project-web/input/rfcs/index.html": [
			9
		]
	},
	"gmpls": {
		"https://usf-cs272-spring2022.github.io/project-web/input/rfcs/index.html": [
			39
		]
	},
	"http": {
		"https://usf-cs272-spring2022.github.io/project-web/input/rfcs/index.html": [
			51
		]
	},
	"hypertext": {
		"https://usf-cs272-spring2022.github.io/project-web/input/rfcs/index.html": [
			48
		]
	},
	"identifi": {
		"https://usf-cs272-spring2022.github.io/project-web/input/rfcs/index.html": [
			17
		]
	},
	"in": {
		"https://usf-cs272-spring2022.github.io/project-web/input/rfcs/index.html": [
			36
		]
	},
	"iso": {
		"https://usf-cs272-spring2022.github.io/project-web/input/rfcs/index.html": [
			7
		]
	},
	"languag": {
		"https://usf-cs272-spring2022.github.io/project-web/input/rfcs/index.html": [
			18
		]
	},
	"mail": {
		"https://usf-cs272-spring2022.github.io/project-web/input/rfcs/index.html": [
			12
		]
	},
	"media": {
		"https://usf-cs272-spring2022.github.io/project-web/input/rfcs/index.html": [
			41
		]
	},
	"mpls": {
		"https://usf-cs272-spring2022.github.io/project-web/input/rfcs/index.html": [
			37
		]
	},
	"network": {
		"https://usf-cs272-spring2022.github.io/project-web/input/rfcs/index.html": [
			11
		]
	},
	"of": {
		"https://usf-cs272-spring2022.github.io/project-web/input/rfcs/index.html": [
			6,
			22,
			31,
			34
		]
	},
	"path": {
		"https://usf-cs272-spring2022.github.io/project-web/input/rfcs/index.html": [
			24
		]
	},
	"procedur": {
		"https://usf-cs272-spring2022.github.io/project-web/input/rfcs/index.html": [
			46
		]
	},
	"protocol": {
		"https://usf-cs272-spring2022.github.io/project-web/input/rfcs/index.html": [
			50
		]
	},
	"registr": {
		"https://usf-cs272-spring2022.github.io/project-web/input/rfcs/index.html": [
			45
		]
	},
	"rfc": {
		"https://usf-cs272-spring2022.github.io/project-web/input/rfcs/index.html": [
			8,
			14,
			19,
			40,
			47
		]
	},
	"rfcs": {
		"https://usf-cs272-spring2022.github.io/project-web/input/rfcs/index.html": [
			1
		]
	},
	"semant": {
		"https://usf-cs272-spring2022.github.io/project-web/input/rfcs/index.html": [
			52
		]
	},
	"sequenc": {
		"https://usf-cs272-spring2022.github.io/project-web/input/rfcs/index.html": [
			33
		]
	},
	"specif": {
		"https://usf-cs272-spring2022.github.io/project-web/input/rfcs/index.html": [
			43
		]
	},
	"system": {
		"https://usf-cs272-spring2022.github.io/project-web/input/rfcs/index.html": [
			13
		]
	},
	"tag": {
		"https://usf-cs272-spring2022.github.io/project-web/input/rfcs/index.html": [
			15
		]
	},
	"the": {
		"https://usf-cs272-spring2022.github.io/project-web/input/rfcs/index.html": [
			20,
			23,
			29
		]
	},
	"to": {
		"https://usf-cs272-spring2022.github.io/project-web/input/rfcs/index.html": [
			28
		]
	},
	"top": {
		"https://usf-cs272-spring2022.github.io/project-web/input/rfcs/index.html": [
			55
		]
	},
	"transfer": {
		"https://usf-cs272-spring2022.github.io/project-web/input/rfcs/index.html": [
			49
		]
	},
	"transform": {
		"https://usf-cs272-spring2022.github.io/project-web/input/rfcs/index.html": [
			4
		]
	},
	"type": {
		"https://usf-cs272-spring2022.github.io/project-web/input/rfcs/index.html": [
			42
		]
	},
	"utf": {
		"https://usf-cs272-spring2022.github.io/project-web/input/rfcs/index.html": [
			2
		]
	}
}